<list xmlns:xsi="http://www.w3.org/2001/XMLSchema-instance" xsi:noNamespaceSchemaLocation="../../xsd/items.xsd">
	<item id="8700" type="EtcItem" name="Receita: Lança de Tiphon (60%)">
		
		<set name="icon" val="icon.etc_recipe_violet_i00" />
		<set name="item_type" val="recipe" />
		<set name="desc" val="Apenas para Anões. Receita para fazer Lança de Tiphon. Requer Criar Item - Nível de Habilidade 8. Taxa de sucesso de 60%." />
		<set name="weight" val="30" />
		<set name="consume_type" val="stackable" />
	</item>
	<item id="8701" type="EtcItem" name="Receita: Lança de Tiphon (100%)">
		
		<set name="icon" val="icon.etc_recipe_violet_i00" />
		<set name="item_type" val="recipe" />
		<set name="desc" val="Apenas para Anões. Receita para fazer Lança de Tiphon. Requer Criar Item - Nível de Habilidade 8. Taxa de sucesso de 100%." />
		<set name="weight" val="30" />
		<set name="consume_type" val="stackable" />
	</item>
	<item id="8702" type="EtcItem" name="Receita: Arco de Shyeed (60%)">
		
		<set name="icon" val="icon.etc_recipe_violet_i00" />
		<set name="item_type" val="recipe" />
		<set name="desc" val="Apenas para Anões. Receita para fazer o Arco de Shyeed. Requer Criar Item - Nível de Habilidade 8. Taxa de sucesso de 60%." />
		<set name="weight" val="30" />
		<set name="consume_type" val="stackable" />
		<set name="price" val="706000" />
	</item>
	<item id="8703" type="EtcItem" name="Receita: Arco de Shyeed (100%)">
		
		<set name="icon" val="icon.etc_recipe_violet_i00" />
		<set name="item_type" val="recipe" />
		<set name="desc" val="Apenas para Anões. Receita para fazer o Arco de Shyeed. Requer Criar Item - Nível de Habilidade 8. Taxa de sucesso de 100%." />
		<set name="weight" val="30" />
		<set name="consume_type" val="stackable" />
		<set name="price" val="706000" />
	</item>
	<item id="8704" type="EtcItem" name="Receita: Furacão de Sobekk (60%)">
		
		<set name="icon" val="icon.etc_recipe_violet_i00" />
		<set name="item_type" val="recipe" />
		<set name="desc" val="Apenas para Anões. Receita para fazer o Furacão de Sobekk. Requer Criar Item - Nível de Habilidade 8. Taxa de sucesso de 60%." />
		<set name="weight" val="30" />
		<set name="consume_type" val="stackable" />
	</item>
	<item id="8705" type="EtcItem" name="Receita: Furacão de Sobekk (100%)">
		
		<set name="icon" val="icon.etc_recipe_violet_i00" />
		<set name="item_type" val="recipe" />
		<set name="desc" val="Apenas para Anões. Receita para fazer o Furacão de Sobekk. Requer Criar Item - Nível de Habilidade 8. Taxa de sucesso de 100%." />
		<set name="weight" val="30" />
		<set name="consume_type" val="stackable" />
	</item>
	<item id="8706" type="EtcItem" name="Receita: Língua de Themis (60%)">
		
		<set name="icon" val="icon.etc_recipe_violet_i00" />
		<set name="item_type" val="recipe" />
		<set name="desc" val="Apenas para Anões. Receita para fazer a Língua de Themis. Requer Criar Item - Nível de Habilidade 8. Taxa de sucesso de 60%." />
		<set name="weight" val="30" />
		<set name="consume_type" val="stackable" />
	</item>
	<item id="8707" type="EtcItem" name="Receita: Língua de Themis (100%)">
		
		<set name="icon" val="icon.etc_recipe_violet_i00" />
		<set name="item_type" val="recipe" />
		<set name="desc" val="Apenas para Anões. Receita para fazer a Língua de Themis. Requer Criar Item - Nível de Habilidade 8. Taxa de sucesso de 100%." />
		<set name="weight" val="30" />
		<set name="consume_type" val="stackable" />
	</item>
	<item id="8708" type="EtcItem" name="Receita: Mão de Cabrio (60%)">
		
		<set name="icon" val="icon.etc_recipe_violet_i00" />
		<set name="item_type" val="recipe" />
		<set name="desc" val="Apenas para Anões. Receita para fazer Mão de Cabrio. Requer Criar Item - Nível de Habilidade 8. Taxa de sucesso de 60%." />
		<set name="weight" val="30" />
		<set name="consume_type" val="stackable" />
	</item>
	<item id="8709" type="EtcItem" name="Receita: Mão de Cabrio (100%)">
		
		<set name="icon" val="icon.etc_recipe_violet_i00" />
		<set name="item_type" val="recipe" />
		<set name="desc" val="Apenas para Anões. Receita para fazer Mão de Cabrio. Requer Criar Item - Nível de Habilidade 8. Taxa de sucesso de 100%." />
		<set name="weight" val="30" />
		<set name="consume_type" val="stackable" />
	</item>
	<item id="8710" type="EtcItem" name="Receita: Cristal de Daimon (60%)">
		
		<set name="icon" val="icon.etc_recipe_violet_i00" />
		<set name="item_type" val="recipe" />
		<set name="desc" val="Apenas para Anões. Receita para fazer um Cristal Demoníaco. Requer Criar Item - Nível de Habilidade 8. Taxa de sucesso de 60%." />
		<set name="weight" val="30" />
		<set name="consume_type" val="stackable" />
	</item>
	<item id="8711" type="EtcItem" name="Receita: Cristal de Daimon (100%)">
		
		<set name="icon" val="icon.etc_recipe_violet_i00" />
		<set name="item_type" val="recipe" />
		<set name="desc" val="Apenas para Anões. Receita para fazer um Cristal de Daimon. Requer Criar Item - Nível de Habilidade 8. Taxa de sucesso de 100%." />
		<set name="weight" val="30" />
		<set name="consume_type" val="stackable" />
	</item>
	<item id="8712" type="EtcItem" name="Fio da Lâmina de Sirra">
		
		<set name="icon" val="icon.etc_sword_body_i00" />
		<set name="item_type" val="material" />
		<set name="desc" val="Um ingrediente essencial necessário para um Anão fazer a Lâmina de Sirra. Pode ser vendido em uma loja regular." />
		<set name="weight" val="60" />
		<set name="consume_type" val="stackable" />
	</item>
	<item id="8713" type="EtcItem" name="Espada de Ipos Lâmina">
		
		<set name="icon" val="icon.etc_sword_body_i00" />
		<set name="item_type" val="material" />
		<set name="desc" val="Um ingrediente essencial necessário para um Anão fazer a Espada de Ipos. Pode ser vendido em uma loja regular." />
		<set name="weight" val="60" />
		<set name="consume_type" val="stackable" />
	</item>
	<item id="8714" type="EtcItem" name="Machado de Barakiel">
		
		<set name="icon" val="icon.etc_bark_gold_i00" />
		<set name="item_type" val="material" />
		<set name="desc" val="Um ingrediente essencial necessário para um Anão fazer o Machado de Barakiel. Pode ser vendido em uma loja regular." />
		<set name="weight" val="60" />
		<set name="consume_type" val="stackable" />
	</item>
	<item id="8715" type="EtcItem" name="Pedaço de Diapasão de Behemoth">
		
		<set name="icon" val="icon.etc_bark_gold_i00" />
		<set name="item_type" val="material" />
		<set name="desc" val="Um ingrediente essencial necessário para um anão fazer o diapasão de Behemoth. Pode ser vendido em uma loja regular." />
		<set name="weight" val="60" />
		<set name="consume_type" val="stackable" />
	</item>
	<item id="8716" type="EtcItem" name="Peça da Tempestade de Naga">
		
		<set name="icon" val="icon.etc_bark_gold_i00" />
		<set name="item_type" val="material" />
		<set name="desc" val="Um ingrediente essencial necessário para um Anão fazer a Tempestade de Naga. Pode ser vendido em uma loja regular." />
		<set name="weight" val="60" />
		<set name="consume_type" val="stackable" />
	</item>
	<item id="8717" type="EtcItem" name="Ponta da Lança de Tiphon">
		
		<set name="icon" val="icon.etc_sword_body_i00" />
		<set name="item_type" val="material" />
		<set name="desc" val="Um ingrediente essencial necessário para um Anão fazer a Lança de Tiphon. Pode ser vendido em uma loja regular." />
		<set name="weight" val="60" />
		<set name="consume_type" val="stackable" />
	</item>
	<item id="8718" type="EtcItem" name="Pressa do Arco de Shyeed">
		
		<set name="icon" val="icon.etc_branch_gold_i00" />
		<set name="item_type" val="material" />
		<set name="desc" val="Um ingrediente essencial necessário para um Anão fazer o Arco de Shyeed. Pode ser vendido em uma loja regular." />
		<set name="weight" val="60" />
		<set name="consume_type" val="stackable" />
	</item>
	<item id="8719" type="EtcItem" name="Gume do Furacão de Sobekk">
		
		<set name="icon" val="icon.etc_sword_body_i00" />
		<set name="item_type" val="material" />
		<set name="desc" val="Um ingrediente essencial necessário para um Anão fazer o Furacão de Sobekk. Pode ser vendido em uma loja regular." />
		<set name="weight" val="60" />
		<set name="consume_type" val="stackable" />
	</item>
	<item id="8720" type="EtcItem" name="Pedaço de Língua de Themis">
		
		<set name="icon" val="icon.etc_bark_gold_i00" />
		<set name="item_type" val="material" />
		<set name="desc" val="Um ingrediente essencial necessário para um anão fazer a língua de Themis. Pode ser vendido em uma loja regular." />
		<set name="weight" val="60" />
		<set name="consume_type" val="stackable" />
	</item>
	<item id="8721" type="EtcItem" name="Cabeça de Mão de Cabrio">
		
		<set name="icon" val="icon.etc_squares_gray_i00" />
		<set name="item_type" val="material" />
		<set name="desc" val="Um ingrediente essencial necessário para um Anão fazer a Mão de Cabrio. Pode ser vendido em uma loja regular." />
		<set name="weight" val="60" />
		<set name="consume_type" val="stackable" />
	</item>
	<item id="8722" type="EtcItem" name="Fragmento de Cristal de Daimon">
		
		<set name="icon" val="icon.etc_bark_gold_i00" />
		<set name="item_type" val="material" />
		<set name="desc" val="Um ingrediente essencial necessário para um Anão fazer o Cristal de Daimon. Pode ser vendido em uma loja regular." />
		<set name="weight" val="60" />
		<set name="consume_type" val="stackable" />
	</item>
	<item id="8723" type="EtcItem" name="Pedra da Vida: Nível 46">
		
		<set name="icon" val="icon.etc_mineral_general_i00" />
		<set name="item_type" val="none" />
		<set name="desc" val="Um Minério comum que foi petrificado pelo dano físico ou mágico de uma criatura. Componente-chave usado no aprimoramento de armas por personagens de nível 46 e acima." />
		<set name="weight" val="2" />
		<set name="consume_type" val="normal" />
		<set name="price" val="5000" />
	</item>
	<item id="8724" type="EtcItem" name="Pedra da Vida: Nível 49">
		
		<set name="icon" val="icon.etc_mineral_general_i00" />
		<set name="item_type" val="none" />
		<set name="desc" val="Um Minério comum que foi petrificado pelo dano físico ou mágico de uma criatura. Componente-chave usado no aprimoramento de armas por personagens de nível 49 e acima." />
		<set name="weight" val="2" />
		<set name="consume_type" val="normal" />
		<set name="price" val="6000" />
	</item>
	<item id="8725" type="EtcItem" name="Pedra da Vida: Nível 52">
		
		<set name="icon" val="icon.etc_mineral_general_i00" />
		<set name="item_type" val="none" />
		<set name="desc" val="Um Minério comum que foi petrificado pelo dano físico ou mágico de uma criatura. Componente-chave usado no aprimoramento de armas por personagens de nível 52 e acima." />
		<set name="weight" val="2" />
		<set name="consume_type" val="normal" />
		<set name="price" val="7200" />
	</item>
	<item id="8726" type="EtcItem" name="Pedra da Vida: Nível 55">
		
		<set name="icon" val="icon.etc_mineral_general_i00" />
		<set name="item_type" val="none" />
		<set name="desc" val="Um Minério comum que foi petrificado pelo dano físico ou mágico de uma criatura. Componente-chave usado no aprimoramento de armas por personagens de nível 55 e acima." />
		<set name="weight" val="2" />
		<set name="consume_type" val="normal" />
		<set name="price" val="8640" />
	</item>
	<item id="8727" type="EtcItem" name="Pedra da Vida: Nível 58">
		
		<set name="icon" val="icon.etc_mineral_general_i01" />
		<set name="item_type" val="none" />
		<set name="desc" val="Um Minério comum que foi petrificado pelo dano físico ou mágico de uma criatura. Componente-chave usado no aprimoramento de armas por personagens de nível 58 e acima." />
		<set name="weight" val="2" />
		<set name="consume_type" val="normal" />
		<set name="price" val="10000" />
	</item>
	<item id="8728" type="EtcItem" name="Pedra da Vida: Nível 61">
		
		<set name="icon" val="icon.etc_mineral_general_i01" />
		<set name="item_type" val="none" />
		<set name="desc" val="Um Minério comum que foi petrificado pelo dano físico ou mágico de uma criatura. Componente-chave usado no aprimoramento de armas por personagens de nível 61 e acima." />
		<set name="weight" val="2" />
		<set name="consume_type" val="normal" />
		<set name="price" val="12000" />
	</item>
	<item id="8729" type="EtcItem" name="Pedra da Vida: Nível 64">
		
		<set name="icon" val="icon.etc_mineral_general_i02" />
		<set name="item_type" val="none" />
		<set name="desc" val="Um Minério comum que foi petrificado pelo dano físico ou mágico de uma criatura. Componente-chave usado no aprimoramento de armas por personagens de nível 64 e acima." />
		<set name="weight" val="2" />
		<set name="consume_type" val="normal" />
		<set name="price" val="15000" />
	</item>
	<item id="8730" type="EtcItem" name="Pedra da Vida: Nível 67">
		
		<set name="icon" val="icon.etc_mineral_general_i02" />
		<set name="item_type" val="none" />
		<set name="desc" val="Um Minério comum que foi petrificado pelo dano físico ou mágico de uma criatura. Componente-chave usado no aprimoramento de armas por personagens de nível 67 e acima." />
		<set name="weight" val="2" />
		<set name="consume_type" val="normal" />
		<set name="price" val="18000" />
	</item>
	<item id="8731" type="EtcItem" name="Pedra da Vida: Nível 70">
		
		<set name="icon" val="icon.etc_mineral_general_i02" />
		<set name="item_type" val="none" />
		<set name="desc" val="Um Minério comum que foi petrificado pelo dano físico ou mágico de uma criatura. Componente-chave usado no aprimoramento de armas por personagens de nível 70 e acima." />
		<set name="weight" val="2" />
		<set name="consume_type" val="normal" />
		<set name="price" val="21600" />
	</item>
	<item id="8732" type="EtcItem" name="Pedra da Vida: Nível 76">
		
		<set name="icon" val="icon.etc_mineral_general_i03" />
		<set name="item_type" val="none" />
		<set name="desc" val="Um Minério comum que foi petrificado pelo dano físico ou mágico de uma criatura. Componente-chave usado no aprimoramento de armas por personagens de nível 76 e acima." />
		<set name="weight" val="2" />
		<set name="consume_type" val="normal" />
		<set name="price" val="24000" />
	</item>
	<item id="8733" type="EtcItem" name="Pedra da Vida Nível Médio: Nível 46">
		
		<set name="icon" val="icon.etc_mineral_special_i00" />
		<set name="item_type" val="none" />
		<set name="desc" val="Um Minério de grau médio que foi petrificado pelo dano físico ou mágico de uma criatura. Componente-chave usado no aprimoramento de armas por personagens de nível 46 e acima." />
		<set name="weight" val="2" />
		<set name="consume_type" val="normal" />
		<set name="price" val="20000" />
	</item>
	<item id="8734" type="EtcItem" name="Pedra da Vida Nível Médio: Nível 49">
		
		<set name="icon" val="icon.etc_mineral_special_i00" />
		<set name="item_type" val="none" />
		<set name="desc" val="Um Minério de grau médio que foi petrificado pelo dano físico ou mágico de uma criatura. Componente-chave usado no aprimoramento de armas por personagens de nível 49 e acima." />
		<set name="weight" val="2" />
		<set name="consume_type" val="normal" />
		<set name="price" val="24000" />
	</item>
	<item id="8735" type="EtcItem" name="Pedra da Vida Nível Médio: Nível 52">
		
		<set name="icon" val="icon.etc_mineral_special_i00" />
		<set name="item_type" val="none" />
		<set name="desc" val="Um Minério de grau médio que foi petrificado pelo dano físico ou mágico de uma criatura. Componente-chave usado no aprimoramento de armas por personagens de nível 52 e acima." />
		<set name="weight" val="2" />
		<set name="consume_type" val="normal" />
		<set name="price" val="28800" />
	</item>
	<item id="8736" type="EtcItem" name="Pedra da Vida Nível Médio: Nível 55">
		
		<set name="icon" val="icon.etc_mineral_special_i00" />
		<set name="item_type" val="none" />
		<set name="desc" val="Um Minério de grau médio que foi petrificado pelo dano físico ou mágico de uma criatura. Componente-chave usado no aprimoramento de armas por personagens de nível 55 e acima." />
		<set name="weight" val="2" />
		<set name="consume_type" val="normal" />
		<set name="price" val="34560" />
	</item>
	<item id="8737" type="EtcItem" name="Pedra da Vida Nível Médio: Nível 58">
		
		<set name="icon" val="icon.etc_mineral_special_i01" />
		<set name="item_type" val="none" />
		<set name="desc" val="Um Minério de grau médio que foi petrificado pelo dano físico ou mágico de uma criatura. Componente-chave usado no aprimoramento de armas por personagens de nível 58 e acima." />
		<set name="weight" val="2" />
		<set name="consume_type" val="normal" />
		<set name="price" val="40000" />
	</item>
	<item id="8738" type="EtcItem" name="Pedra da Vida Nível Médio: Nível 61">
		
		<set name="icon" val="icon.etc_mineral_special_i01" />
		<set name="item_type" val="none" />
		<set name="desc" val="Um Minério de grau médio que foi petrificado pelo dano físico ou mágico de uma criatura. Componente-chave usado no aprimoramento de armas por personagens de nível 61 e acima." />
		<set name="weight" val="2" />
		<set name="consume_type" val="normal" />
		<set name="price" val="48000" />
	</item>
	<item id="8739" type="EtcItem" name="Pedra da Vida Nível Médio: Nível 64">
		
		<set name="icon" val="icon.etc_mineral_special_i02" />
		<set name="item_type" val="none" />
		<set name="desc" val="Um Minério de grau médio que foi petrificado pelo dano físico ou mágico de uma criatura. Componente-chave usado no aprimoramento de armas por personagens de nível 64 e acima." />
		<set name="weight" val="2" />
		<set name="consume_type" val="normal" />
		<set name="price" val="60000" />
	</item>
	<item id="8740" type="EtcItem" name="Pedra da Vida Nível Médio: Nível 67">
		
		<set name="icon" val="icon.etc_mineral_special_i02" />
		<set name="item_type" val="none" />
		<set name="desc" val="Um Minério de grau médio que foi petrificado pelo dano físico ou mágico de uma criatura. Componente-chave usado no aprimoramento de armas por personagens de nível 67 e acima." />
		<set name="weight" val="2" />
		<set name="consume_type" val="normal" />
		<set name="price" val="72000" />
	</item>
	<item id="8741" type="EtcItem" name="Pedra da Vida Nível Médio: Nível 70">
		
		<set name="icon" val="icon.etc_mineral_special_i02" />
		<set name="item_type" val="none" />
		<set name="desc" val="Um Minério de grau médio que foi petrificado pelo dano físico ou mágico de uma criatura. Componente-chave usado no aprimoramento de armas por personagens de nível 70 e acima." />
		<set name="weight" val="2" />
		<set name="consume_type" val="normal" />
		<set name="price" val="86400" />
	</item>
	<item id="8742" type="EtcItem" name="Pedra da Vida Nível Médio: Nível 76">
		
		<set name="icon" val="icon.etc_mineral_special_i03" />
		<set name="item_type" val="none" />
		<set name="desc" val="Um Minério de grau médio que foi petrificado pelo dano físico ou mágico de uma criatura. Componente-chave usado no aprimoramento de armas por personagens de nível 76 e acima." />
		<set name="weight" val="2" />
		<set name="consume_type" val="normal" />
		<set name="price" val="96000" />
	</item>
	<item id="8743" type="EtcItem" name="Pedra da Vida Nível Alto: Nível 46">
		
		<set name="icon" val="icon.etc_mineral_rare_i00" />
		<set name="item_type" val="none" />
		<set name="desc" val="Um Minério de alto grau que foi petrificado pelo dano físico ou mágico de uma criatura. Componente-chave usado no aprimoramento de armas por personagens de nível 46 e acima." />
		<set name="weight" val="2" />
		<set name="consume_type" val="normal" />
		<set name="price" val="200000" />
	</item>
	<item id="8744" type="EtcItem" name="Pedra da Vida Nível Alto: Nível 49">
		
		<set name="icon" val="icon.etc_mineral_rare_i00" />
		<set name="item_type" val="none" />
		<set name="desc" val="Um Minério de alto grau que foi petrificado pelo dano físico ou mágico de uma criatura. Componente-chave usado no aprimoramento de armas por personagens de nível 49 e acima." />
		<set name="weight" val="2" />
		<set name="consume_type" val="normal" />
		<set name="price" val="240000" />
	</item>
	<item id="8745" type="EtcItem" name="Pedra da Vida Nível Alto: Nível 52">
		
		<set name="icon" val="icon.etc_mineral_rare_i00" />
		<set name="item_type" val="none" />
		<set name="desc" val="Um Minério de alto grau que foi petrificado pelo dano físico ou mágico de uma criatura. Componente-chave usado no aprimoramento de armas por personagens de nível 52 e acima." />
		<set name="weight" val="2" />
		<set name="consume_type" val="normal" />
		<set name="price" val="288000" />
	</item>
	<item id="8746" type="EtcItem" name="Pedra da Vida Nível Alto: Nível 55">
		
		<set name="icon" val="icon.etc_mineral_rare_i00" />
		<set name="item_type" val="none" />
		<set name="desc" val="Um Minério de alto grau que foi petrificado pelo dano físico ou mágico de uma criatura. Componente-chave usado no aprimoramento de armas por personagens de nível 55 e acima." />
		<set name="weight" val="2" />
		<set name="consume_type" val="normal" />
		<set name="price" val="345600" />
	</item>
	<item id="8747" type="EtcItem" name="Pedra da Vida Nível Alto: Nível 58">
		
		<set name="icon" val="icon.etc_mineral_rare_i01" />
		<set name="item_type" val="none" />
		<set name="desc" val="Um Minério de alto grau que foi petrificado pelo dano físico ou mágico de uma criatura. Componente-chave usado no aprimoramento de armas por personagens de nível 58 e acima." />
		<set name="weight" val="2" />
		<set name="consume_type" val="normal" />
		<set name="price" val="400000" />
	</item>
	<item id="8748" type="EtcItem" name="Pedra da Vida Nível Alto: Nível 61">
		
		<set name="icon" val="icon.etc_mineral_rare_i01" />
		<set name="item_type" val="none" />
		<set name="desc" val="Um Minério de alto grau que foi petrificado pelo dano físico ou mágico de uma criatura. Componente-chave usado no aprimoramento de armas por personagens de nível 61 e acima." />
		<set name="weight" val="2" />
		<set name="consume_type" val="normal" />
		<set name="price" val="480000" />
	</item>
	<item id="8749" type="EtcItem" name="Pedra da Vida Nível Alto: Nível 64">
		
		<set name="icon" val="icon.etc_mineral_rare_i02" />
		<set name="item_type" val="none" />
		<set name="desc" val="Um Minério de alto grau que foi petrificado pelo dano físico ou mágico de uma criatura. Componente-chave usado no aprimoramento de armas por personagens de nível 64 e acima." />
		<set name="weight" val="2" />
		<set name="consume_type" val="normal" />
		<set name="price" val="600000" />
	</item>
	<item id="8750" type="EtcItem" name="Pedra da Vida Nível Alto: Nível 67">
		
		<set name="icon" val="icon.etc_mineral_rare_i02" />
		<set name="item_type" val="none" />
		<set name="desc" val="Um Minério de alto grau que foi petrificado pelo dano físico ou mágico de uma criatura. Componente-chave usado no aprimoramento de armas por personagens de nível 67 e acima." />
		<set name="weight" val="2" />
		<set name="consume_type" val="normal" />
		<set name="price" val="720000" />
	</item>
	<item id="8751" type="EtcItem" name="Pedra da Vida Nível Alto: Nível 70">
		
		<set name="icon" val="icon.etc_mineral_rare_i02" />
		<set name="item_type" val="none" />
		<set name="desc" val="Um Minério de alto grau que foi petrificado pelo dano físico ou mágico de uma criatura. Componente-chave usado no aprimoramento de armas por personagens de nível 70 e acima." />
		<set name="weight" val="2" />
		<set name="consume_type" val="normal" />
		<set name="price" val="864000" />
	</item>
	<item id="8752" type="EtcItem" name="Pedra da Vida Nível Alto: Nível 76">
		
		<set name="icon" val="icon.etc_mineral_rare_i03" />
		<set name="item_type" val="none" />
		<set name="desc" val="Um Minério de alto grau que foi petrificado pelo dano físico ou mágico de uma criatura. Componente-chave usado no aprimoramento de armas por personagens de nível 76 e acima." />
		<set name="weight" val="2" />
		<set name="consume_type" val="normal" />
		<set name="price" val="960000" />
	</item>
	<item id="8753" type="EtcItem" name="Pedra da Vida Nível Alto: Nível 46">
		
		<set name="icon" val="icon.etc_mineral_unique_i00" />
		<set name="item_type" val="none" />
		<set name="desc" val="O Minério de maior qualidade disponível que foi petrificado pelo dano físico ou mágico de uma criatura. Componente-chave usado no aprimoramento de armas por personagens de nível 46 e acima." />
		<set name="weight" val="2" />
		<set name="consume_type" val="normal" />
		<set name="price" val="1000000" />
	</item>
	<item id="8754" type="EtcItem" name="Pedra da Vida Nível Alto: Nível 49">
		
		<set name="icon" val="icon.etc_mineral_unique_i00" />
		<set name="item_type" val="none" />
		<set name="desc" val="O Minério de maior qualidade disponível que foi petrificado pelo dano físico ou mágico de uma criatura. Componente-chave usado no aprimoramento de armas por personagens de nível 49 e acima." />
		<set name="weight" val="2" />
		<set name="consume_type" val="normal" />
		<set name="price" val="1200000" />
	</item>
	<item id="8755" type="EtcItem" name="Pedra da Vida Nível Alto: Nível 52">
		
		<set name="icon" val="icon.etc_mineral_unique_i00" />
		<set name="item_type" val="none" />
		<set name="desc" val="O Minério de maior qualidade disponível que foi petrificado pelo dano físico ou mágico de uma criatura. Componente-chave usado no aprimoramento de armas por personagens de nível 52 e acima." />
		<set name="weight" val="2" />
		<set name="consume_type" val="normal" />
		<set name="price" val="1440000" />
	</item>
	<item id="8756" type="EtcItem" name="Pedra da Vida Nível Alto: Nível 55">
		
		<set name="icon" val="icon.etc_mineral_unique_i00" />
		<set name="item_type" val="none" />
		<set name="desc" val="O Minério de maior qualidade disponível que foi petrificado pelo dano físico ou mágico de uma criatura. Componente-chave usado no aprimoramento de armas por personagens de nível 55 e acima." />
		<set name="weight" val="2" />
		<set name="consume_type" val="normal" />
		<set name="price" val="1728000" />
	</item>
	<item id="8757" type="EtcItem" name="Pedra da Vida Nível Alto: Nível 58">
		
		<set name="icon" val="icon.etc_mineral_unique_i01" />
		<set name="item_type" val="none" />
		<set name="desc" val="O Minério de maior qualidade disponível que foi petrificado pelo dano físico ou mágico de uma criatura. Componente-chave usado no aprimoramento de armas por personagens de nível 58 e acima." />
		<set name="weight" val="2" />
		<set name="consume_type" val="normal" />
		<set name="price" val="2000000" />
	</item>
	<item id="8758" type="EtcItem" name="Pedra da Vida Nível Alto: Nível 61">
		
		<set name="icon" val="icon.etc_mineral_unique_i01" />
		<set name="item_type" val="none" />
		<set name="desc" val="O Minério de maior qualidade disponível que foi petrificado pelo dano físico ou mágico de uma criatura. Componente-chave usado no aprimoramento de armas por personagens de nível 61 e acima." />
		<set name="weight" val="2" />
		<set name="consume_type" val="normal" />
		<set name="price" val="2400000" />
	</item>
	<item id="8759" type="EtcItem" name="Pedra da Vida Nível Alto: Nível 64">
		
		<set name="icon" val="icon.etc_mineral_unique_i02" />
		<set name="item_type" val="none" />
		<set name="desc" val="O Minério de maior qualidade disponível que foi petrificado pelo dano físico ou mágico de uma criatura. Componente-chave usado no aprimoramento de armas por personagens de nível 64 e acima." />
		<set name="weight" val="2" />
		<set name="consume_type" val="normal" />
		<set name="price" val="3000000" />
	</item>
	<item id="8760" type="EtcItem" name="Pedra da Vida Nível Alto: Nível 67">
		
		<set name="icon" val="icon.etc_mineral_unique_i02" />
		<set name="item_type" val="none" />
		<set name="desc" val="O Minério de maior qualidade disponível que foi petrificado pelo dano físico ou mágico de uma criatura. Componente-chave usado no aprimoramento de armas por personagens de nível 67 e acima." />
		<set name="weight" val="2" />
		<set name="consume_type" val="normal" />
		<set name="price" val="3600000" />
	</item>
	<item id="8761" type="EtcItem" name="Pedra da Vida Nível Alto: Nível 70">
		
		<set name="icon" val="icon.etc_mineral_unique_i02" />
		<set name="item_type" val="none" />
		<set name="desc" val="O Minério de maior qualidade disponível que foi petrificado pelo dano físico ou mágico de uma criatura. Componente-chave usado no aprimoramento de armas por personagens de nível 70 e acima." />
		<set name="weight" val="2" />
		<set name="consume_type" val="normal" />
		<set name="price" val="4320000" />
	</item>
	<item id="8762" type="EtcItem" name="Pedra da Vida Nível Alto: Nível 76">
		
		<set name="icon" val="icon.etc_mineral_unique_i03" />
		<set name="item_type" val="none" />
		<set name="desc" val="O Minério de maior qualidade disponível que foi petrificado pelo dano físico ou mágico de uma criatura. Componente-chave usado no aprimoramento de armas por personagens de nível 76 e acima." />
		<set name="weight" val="2" />
		<set name="consume_type" val="normal" />
		<set name="price" val="4800000" />
	</item>
	<item id="8763" type="Weapon" name="Armadilha Elrokiana">
		
		<set name="icon" val="icon.weapon_seize_mace_i00" />
		<set name="bodypart" val="rhand" />
		<set name="desc" val="Arma de armadilha usada na Ilha Primeva." />
		<set name="weight" val="500" />
		<set name="crystal_type" val="a" />
		<set name="weapon_type" val="blunt" />
		<set name="atk_speed" val="379" />
		<for>
			<set val="0" order="0x08" stat="pAtk" />
			<set val="0" order="0x08" stat="mAtk" />
			<set val="0" order="0x08" stat="rCrit" />
			<add val="0" order="0x10" stat="accCombat" />
			<set val="379" order="0x08" stat="pAtkSpd" />
			<enchant val="0" order="0x0C" stat="pAtk" />
			<enchant val="0" order="0x0C" stat="mAtk" />
		</for>
	</item>
	<item id="8764" type="EtcItem" name="Pedra Armadilha">
		
		<set name="icon" val="icon.etc_capture_stone_i00" />
		<set name="item_type" val="none" />
		<set name="desc" val="Uma pedra usada na Armadilha Elrokiana." />
		<set name="weight" val="2" />
		<set name="consume_type" val="stackable" />
		<set name="price" val="500" />
	</item>
	<item id="8765" type="EtcItem" name="Gema Vermelha">
		
		<set name="icon" val="icon.etc_bead_red_i00" />
		<set name="item_type" val="none" />
		<set name="desc" val="Gemas vermelhas brilhantes coletadas pelo Chefe do Armazém Klump da Aden Castle Town. Você pode jogar o jogo de cartas se trouxer para Klump mais de 50 dessas joias." />
		<set name="consume_type" val="stackable" />
	</item>
	<item id="8766" type="EtcItem" name="Pérola Espiritual">
		
		<set name="icon" val="icon.etc_bead_blue_i00" />
		<set name="item_type" val="none" />
		<set name="desc" val="Correntes coletadas pelo Ferreiro Wilbert de Aden Castle Town. Você pode jogar o jogo se trouxer mais de 50 para ele." />
		<set name="consume_type" val="stackable" />
	</item>
	<item id="8767" type="EtcItem" name="Garra de Tiranossauro">
		
		<set name="icon" val="icon.etc_claw_i00" />
		<set name="item_type" val="none" />
		<set name="desc" val="Esta garra pode ser obtida derrotando um Tiranossauro." />
		<set name="consume_type" val="stackable" />
	</item>
	<item id="8768" type="EtcItem" name="Fragmento do Diário">
		
		<set name="icon" val="icon.etc_piece_of_paper_white_i00" />
		<set name="item_type" val="none" />
		<set name="desc" val="Este é um pedaço do diário de um membro da expedição desaparecido. Entregue-o ao líder da expedição, Capitão Marquez." />
		<set name="consume_type" val="stackable" />
	</item>
	<item id="8769" type="EtcItem" name="Carta do Membro da Expedição">
		
		<set name="icon" val="icon.etc_letter_envelope_i00" />
		<set name="item_type" val="none" />
		<set name="desc" val="Esta é uma carta que um membro desaparecido da expedição enviou para seu amigo Elrokian Kirikachin. Entregue para Kirikachin." />
		<set name="consume_type" val="stackable" />
	</item>
	<item id="8770" type="EtcItem" name="Garra de Ornithomimus">
		
		<set name="icon" val="icon.etc_claw_i00" />
		<set name="item_type" val="none" />
		<set name="desc" val="Leve isto para Asamah, o filho do chefe." />
		<set name="consume_type" val="stackable" />
	</item>
	<item id="8771" type="EtcItem" name="Osso de Deinonychus">
		
		<set name="icon" val="icon.etc_piece_bone_red_i00" />
		<set name="item_type" val="none" />
		<set name="desc" val="Leve isto para Asamah, o filho do chefe." />
		<set name="consume_type" val="stackable" />
	</item>
	<item id="8772" type="EtcItem" name="Pele de Paquicefalossauro">
		
		<set name="icon" val="icon.etc_leather_yellow_i00" />
		<set name="item_type" val="none" />
		<set name="desc" val="Leve isto para Asamah, o filho do chefe." />
		<set name="consume_type" val="stackable" />
	</item>
	<item id="8773" type="EtcItem" name="Pratique Armadilha Elrokiana">
		
		<set name="icon" val="icon.weapon_seize_mace_i00" />
		<set name="item_type" val="none" />
		<set name="desc" val="Leve esta armadilha prática, que é necessária para aprender uma habilidade tribal especial de Elrokian, para Kirikachin." />
		<set name="consume_type" val="stackable" />
	</item>
	<item id="8774" type="EtcItem" name="Tecido de Dinossauro">
		
		<set name="icon" val="icon.etc_bodypart_heart_i00" />
		<set name="item_type" val="none" />
		<set name="desc" val="Este Tecido de Dinossauro é um ingrediente de pesquisa para mágicos e artesãos anões." />
		<set name="consume_type" val="stackable" />
	</item>
	<item id="8775" type="EtcItem" name="Ovo de Dinossauro">
		
		<set name="icon" val="icon.etc_dragon_egg_i05" />
		<set name="item_type" val="none" />
		<set name="desc" val="Este Ovo de Dinossauro é um ingrediente de pesquisa (juntamente com Tecido de Dinossauro) para mágicos e artesãos de Anãos." />
		<set name="consume_type" val="stackable" />
	</item>
	<item id="8776" type="EtcItem" name="Ossos de Um Dinossauro das Planícies">
		
		<set name="icon" val="icon.etc_piece_bone_black_i00" />
		<set name="item_type" val="none" />
		<set name="desc" val="Este é um ingrediente de pesquisa para os sacerdotes e mágicos de Shilen." />
		<set name="consume_type" val="stackable" />
	</item>
	<item id="8777" type="EtcItem" name="Criaturas Antigas E Como Desejo Estar Com Elas">
		
		<set name="icon" val="icon.etc_spellbook_gray_i00" />
		<set name="item_type" val="none" />
		<set name="desc" val="Encontrado na biblioteca principal de Rune, este livro contém informações sobre criaturas antigas." />
		<set name="consume_type" val="stackable" />
	</item>
	<item id="8778" type="EtcItem" name="Ovo Mantarasa">
		
		<set name="icon" val="icon.etc_dragon_egg_i03" />
		<set name="item_type" val="none" />
		<set name="desc" val="Este item misterioso pode curar qualquer doença. Pode ser obtido no Lost Nest da Primeval Isle." />
		<set name="consume_type" val="stackable" />
	</item>
	<item id="8779" type="EtcItem" name="Garra de Ornithomimus">
		
		<set name="icon" val="icon.etc_claw_i00" />
		<set name="item_type" val="none" />
		<set name="desc" val="Esta garra de dinossauro pode ser usada pelo Elrokian Xãma Karakawei para realizar um ritual especial." />
		<set name="consume_type" val="stackable" />
	</item>
	<item id="8780" type="EtcItem" name="Fragmento de Osso de Deinonychus">
		
		<set name="icon" val="icon.etc_fang_red_i00" />
		<set name="item_type" val="none" />
		<set name="desc" val="Este fragmento de osso de dinossauro pode ser usado pelo Elrokian Xãma Karakawei para realizar um ritual especial." />
		<set name="consume_type" val="stackable" />
	</item>
	<item id="8781" type="EtcItem" name="Epitáfio da Sabedoria">
		
		<set name="icon" val="icon.etc_ancient_tablet_i00" />
		<set name="item_type" val="none" />
		<set name="desc" val="Este epitáfio pode ser obtido no Pilar da Sabedoria de Chuta Kaimu no Lost Nest." />
		<set name="consume_type" val="stackable" />
	</item>
	<item id="8782" type="EtcItem" name="Fragmento do Gazkh">
		
		<set name="icon" val="icon.etc_piece_of_gazk_i00" />
		<set name="item_type" val="none" />
		<set name="desc" val="Este é um fragmento do machado Gazkh que Shilen deu aos guerreiros Elrokian há muito tempo." />
		<set name="consume_type" val="stackable" />
	</item>
	<item id="8783" type="EtcItem" name="Osso em Pó">
		
		<set name="icon" val="icon.etc_powder_gray_i00" />
		<set name="item_type" val="none" />
		<set name="desc" val="Esses restos semelhantes a cinzas de um antigo guerreiro Elrokiano podem ser obtidos após a realização de um serviço memorial no Túmulo do Guerreiro." />
		<set name="consume_type" val="stackable" />
	</item>
	<item id="8784" type="EtcItem" name="Gazkh">
		
		<set name="icon" val="icon.etc_head_of_gazk_i00" />
		<set name="item_type" val="none" />
		<set name="desc" val="Este antigo machado, Gazkh, pode ser reformado pela Estátua de Pedra de Shilen. É necessário lutar contra Sailren." />
		<set name="consume_type" val="stackable" />
	</item>
	<item id="8785" type="EtcItem" name="Colar Presa de Dinossauro">
		
		<set name="icon" val="icon.etc_ketra_friendship_1_i00" />
		<set name="item_type" val="none" />
		<set name="desc" val="Este colar é a marca dos antigos Elrokians que invadiram o cais." />
		<set name="consume_type" val="stackable" />
	</item>
	<item id="8786" type="EtcItem" name="Poção Primordial">
		
		<set name="icon" val="icon.etc_potion_red_i00" />
		<set name="item_type" val="potion" />
		<set name="desc" val="Aumenta a resistência a venenos e anestesias." />
		<set name="weight" val="2" />
		<set name="consume_type" val="stackable" />
		<set name="price" val="5000" />
	</item>
	<item id="8787" type="EtcItem" name="Fruto do Sprigant">
		
		<set name="icon" val="icon.etc_fruit_green_i00" />
		<set name="item_type" val="potion" />
		<set name="desc" val="Esta fruta, largada por Sprigants, aumenta a resistência a venenos e anestesias." />
		<set name="weight" val="2" />
		<set name="consume_type" val="stackable" />
	</item>
	<item id="8788" type="Weapon" name="Lâmina de Sirra - Pressa">
		
		<set name="icon" val="icon.weapon_sirr_blade_i01" />
		<set name="bodypart" val="rhand" />
		<set name="desc" val="Cristal da Alma: Aumenta o Vel. Atq. por 6%. Aumenta o dano infligido durante o PvP." />
		<set name="crystallizable" val="true" />
		<set name="weight" val="1300" />
		<set name="soulshots" val="1" />
		<set name="spiritshots" val="1" />
		<set name="crystal_type" val="a" />
		<set name="p_dam" val="251" />
		<set name="rnd_dam" val="10" />
		<set name="weapon_type" val="sword" />
		<set name="critical" val="8" />
		<set name="atk_speed" val="379" />
		<set name="m_dam" val="121" />
		<set name="crystal_count" val="2824" />
		<set name="item_skill_id" val="3037" /> 
		<set name="item_skill_lvl" val="6" />
		<for>
			<set val="251" order="0x08" stat="pAtk" />
			<set val="121" order="0x08" stat="mAtk" />
			<set val="8" order="0x08" stat="rCrit" />
			<add val="0" order="0x10" stat="accCombat" />
			<set val="379" order="0x08" stat="pAtkSpd" />
			<enchant val="0" order="0x0C" stat="pAtk" />
			<enchant val="0" order="0x0C" stat="mAtk" />
			
			<mul val="1.05" order="0x30" stat="pvpPhysDmg" />
			<mul val="1.05" order="0x30" stat="pvpMagicalDmg" />
			
			<mul val="1.06" order="0x30" stat="pAtkSpd" />
		</for>
	</item>
	<item id="8789" type="Weapon" name="Lâmina de Sirra - Vida">
		
		<set name="icon" val="icon.weapon_sirr_blade_i01" />
		<set name="bodypart" val="rhand" />
		<set name="desc" val="Cristal da Alma: Aumenta o HP máximo em 25%. Aumenta o dano infligido durante o PvP." />
		<set name="crystallizable" val="true" />
		<set name="weight" val="1300" />
		<set name="soulshots" val="1" />
		<set name="spiritshots" val="1" />
		<set name="crystal_type" val="a" />
		<set name="p_dam" val="251" />
		<set name="rnd_dam" val="10" />
		<set name="weapon_type" val="sword" />
		<set name="critical" val="8" />
		<set name="atk_speed" val="379" />
		<set name="m_dam" val="121" />
		<set name="crystal_count" val="2824" />
		<set name="item_skill_id" val="3013" /> 
		<set name="item_skill_lvl" val="4" />
		<for>
			<set val="251" order="0x08" stat="pAtk" />
			<set val="121" order="0x08" stat="mAtk" />
			<set val="8" order="0x08" stat="rCrit" />
			<add val="0" order="0x10" stat="accCombat" />
			<set val="379" order="0x08" stat="pAtkSpd" />
			<enchant val="0" order="0x0C" stat="pAtk" />
			<enchant val="0" order="0x0C" stat="mAtk" />
			
			<mul val="1.05" order="0x30" stat="pvpPhysDmg" />
			<mul val="1.05" order="0x30" stat="pvpMagicalDmg" />
		</for>
	</item>
	<item id="8790" type="Weapon" name="Lâmina de Sirra - Veneno Crítico">
		
		<set name="icon" val="icon.weapon_sirr_blade_i01" />
		<set name="bodypart" val="rhand" />
		<set name="desc" val="Cristal da Alma: Aumenta a possibilidade de o alvo ser envenenado em 15% durante um ataque crítico regular. Aumenta o dano infligido durante o PvP." />
		<set name="crystallizable" val="true" />
		<set name="weight" val="1300" />
		<set name="soulshots" val="1" />
		<set name="spiritshots" val="1" />
		<set name="crystal_type" val="a" />
		<set name="p_dam" val="251" />
		<set name="rnd_dam" val="10" />
		<set name="weapon_type" val="sword" />
		<set name="critical" val="8" />
		<set name="atk_speed" val="379" />
		<set name="m_dam" val="121" />
		<set name="crystal_count" val="2824" />
		<set name="onCrit_skill_id" val="3024" /> 
		<set name="onCrit_skill_lvl" val="6" />
		<set name="onCrit_skill_chance" val="15" />
		<for>
			<set val="251" order="0x08" stat="pAtk" />
			<set val="121" order="0x08" stat="mAtk" />
			<set val="8" order="0x08" stat="rCrit" />
			<add val="0" order="0x10" stat="accCombat" />
			<set val="379" order="0x08" stat="pAtkSpd" />
			<enchant val="0" order="0x0C" stat="pAtk" />
			<enchant val="0" order="0x0C" stat="mAtk" />
			
			<mul val="1.05" order="0x30" stat="pvpPhysDmg" />
			<mul val="1.05" order="0x30" stat="pvpMagicalDmg" />
		</for>
	</item>
	<item id="8791" type="Weapon" name="Espada de Ipos - Foco">
		
		<set name="icon" val="icon.weapon_sword_of_ipos_i01" />
		<set name="bodypart" val="lrhand" />
		<set name="desc" val="Cristal da Alma: Aumenta o Crítico em 61. Aumenta o dano infligido durante o PvP." />
		<set name="crystallizable" val="true" />
		<set name="weight" val="1820" />
		<set name="soulshots" val="1" />
		<set name="spiritshots" val="1" />
		<set name="crystal_type" val="a" />
		<set name="p_dam" val="305" />
		<set name="rnd_dam" val="10" />
		<set name="weapon_type" val="bigsword" />
		<set name="critical" val="8" />
		<set name="atk_speed" val="325" />
		<set name="m_dam" val="121" />
		<set name="crystal_count" val="2824" />
		<set name="item_skill_id" val="3050" /> 
		<set name="item_skill_lvl" val="2" />
		<for>
			<set val="305" order="0x08" stat="pAtk" />
			<set val="121" order="0x08" stat="mAtk" />
			<set val="8" order="0x08" stat="rCrit" />
			<add val="0" order="0x10" stat="accCombat" />
			<set val="325" order="0x08" stat="pAtkSpd" />
			<enchant val="0" order="0x0C" stat="pAtk" />
			<enchant val="0" order="0x0C" stat="mAtk" />
			
			<mul val="1.05" order="0x30" stat="pvpPhysDmg" />
			<mul val="1.05" order="0x30" stat="pvpMagicalDmg" />
			
			<add val="61" order="0x40" stat="rCrit" />
		</for>
	</item>
	<item id="8792" type="Weapon" name="Espada de Ipos - Pressa">
		
		<set name="icon" val="icon.weapon_sword_of_ipos_i01" />
		<set name="bodypart" val="lrhand" />
		<set name="desc" val="Cristal da Alma: Aumenta o Vel. Atq. por 6%. Aumenta o dano infligido durante o PvP." />
		<set name="crystallizable" val="true" />
		<set name="weight" val="1820" />
		<set name="soulshots" val="1" />
		<set name="spiritshots" val="1" />
		<set name="crystal_type" val="a" />
		<set name="p_dam" val="305" />
		<set name="rnd_dam" val="10" />
		<set name="weapon_type" val="bigsword" />
		<set name="critical" val="8" />
		<set name="atk_speed" val="325" />
		<set name="m_dam" val="121" />
		<set name="crystal_count" val="2824" />
		<set name="item_skill_id" val="3037" /> 
		<set name="item_skill_lvl" val="6" />
		<for>
			<set val="305" order="0x08" stat="pAtk" />
			<set val="121" order="0x08" stat="mAtk" />
			<set val="8" order="0x08" stat="rCrit" />
			<add val="0" order="0x10" stat="accCombat" />
			<set val="325" order="0x08" stat="pAtkSpd" />
			<enchant val="0" order="0x0C" stat="pAtk" />
			<enchant val="0" order="0x0C" stat="mAtk" />
			
			<mul val="1.05" order="0x30" stat="pvpPhysDmg" />
			<mul val="1.05" order="0x30" stat="pvpMagicalDmg" />
			
			<mul val="1.06" order="0x30" stat="pAtkSpd" />
		</for>
	</item>
	<item id="8793" type="Weapon" name="Espada de Ipos - Vida">
		
		<set name="icon" val="icon.weapon_sword_of_ipos_i01" />
		<set name="bodypart" val="lrhand" />
		<set name="desc" val="Cristal da Alma: Aumenta o HP máximo em 25%. Aumenta o dano infligido durante o PvP." />
		<set name="crystallizable" val="true" />
		<set name="weight" val="1820" />
		<set name="soulshots" val="1" />
		<set name="spiritshots" val="1" />
		<set name="crystal_type" val="a" />
		<set name="p_dam" val="305" />
		<set name="rnd_dam" val="10" />
		<set name="weapon_type" val="bigsword" />
		<set name="critical" val="8" />
		<set name="atk_speed" val="325" />
		<set name="m_dam" val="121" />
		<set name="crystal_count" val="2824" />
		<set name="item_skill_id" val="3013" /> 
		<set name="item_skill_lvl" val="4" />
		<for>
			<set val="305" order="0x08" stat="pAtk" />
			<set val="121" order="0x08" stat="mAtk" />
			<set val="8" order="0x08" stat="rCrit" />
			<add val="0" order="0x10" stat="accCombat" />
			<set val="325" order="0x08" stat="pAtkSpd" />
			<enchant val="0" order="0x0C" stat="pAtk" />
			<enchant val="0" order="0x0C" stat="mAtk" />
			
			<mul val="1.05" order="0x30" stat="pvpPhysDmg" />
			<mul val="1.05" order="0x30" stat="pvpMagicalDmg" />
		</for>
	</item>
	<item id="8794" type="Weapon" name="Machado de Barakiel - Vida">
		
		<set name="icon" val="icon.weapon_barakiel_axe_i01" />
		<set name="bodypart" val="rhand" />
		<set name="desc" val="Cristal da Alma: Aumenta o HP máximo em 25%. Aumenta o dano infligido durante o PvP." />
		<set name="crystallizable" val="true" />
		<set name="weight" val="1550" />
		<set name="soulshots" val="1" />
		<set name="spiritshots" val="1" />
		<set name="crystal_type" val="a" />
		<set name="p_dam" val="251" />
		<set name="rnd_dam" val="20" />
		<set name="weapon_type" val="blunt" />
		<set name="critical" val="4" />
		<set name="hit_modify" val="4.00000" />
		<set name="atk_speed" val="379" />
		<set name="m_dam" val="121" />
		<set name="crystal_count" val="2824" />
		<set name="item_skill_id" val="3013" /> 
		<set name="item_skill_lvl" val="4" />
		<for>
			<set val="251" order="0x08" stat="pAtk" />
			<set val="121" order="0x08" stat="mAtk" />
			<set val="4" order="0x08" stat="rCrit" />
			<add val="4" order="0x10" stat="accCombat" />
			<set val="379" order="0x08" stat="pAtkSpd" />
			<enchant val="0" order="0x0C" stat="pAtk" />
			<enchant val="0" order="0x0C" stat="mAtk" />
			
			<mul val="1.05" order="0x30" stat="pvpPhysDmg" />
			<mul val="1.05" order="0x30" stat="pvpMagicalDmg" />
		</for>
	</item>
	<item id="8795" type="Weapon" name="Machado de Barakiel - Pressa">
		
		<set name="icon" val="icon.weapon_barakiel_axe_i01" />
		<set name="bodypart" val="rhand" />
		<set name="desc" val="Cristal da Alma: Aumenta o Vel. Atq. por 6%. Aumenta o dano infligido durante o PvP." />
		<set name="crystallizable" val="true" />
		<set name="weight" val="1550" />
		<set name="soulshots" val="1" />
		<set name="spiritshots" val="1" />
		<set name="crystal_type" val="a" />
		<set name="p_dam" val="251" />
		<set name="rnd_dam" val="20" />
		<set name="weapon_type" val="blunt" />
		<set name="critical" val="4" />
		<set name="hit_modify" val="4.00000" />
		<set name="atk_speed" val="379" />
		<set name="m_dam" val="121" />
		<set name="crystal_count" val="2824" />
		<set name="item_skill_id" val="3037" /> 
		<set name="item_skill_lvl" val="6" />
		<for>
			<set val="251" order="0x08" stat="pAtk" />
			<set val="121" order="0x08" stat="mAtk" />
			<set val="4" order="0x08" stat="rCrit" />
			<add val="4" order="0x10" stat="accCombat" />
			<set val="379" order="0x08" stat="pAtkSpd" />
			<enchant val="0" order="0x0C" stat="pAtk" />
			<enchant val="0" order="0x0C" stat="mAtk" />
			
			<mul val="1.05" order="0x30" stat="pvpPhysDmg" />
			<mul val="1.05" order="0x30" stat="pvpMagicalDmg" />
			
			<mul val="1.06" order="0x30" stat="pAtkSpd" />
		</for>
	</item>
	<item id="8796" type="Weapon" name="Machado de Barakiel - Foco">
		
		<set name="icon" val="icon.weapon_barakiel_axe_i01" />
		<set name="bodypart" val="rhand" />
		<set name="desc" val="Cristal da Alma: Aumenta o Crítico em 61. Aumenta o dano infligido durante o PvP." />
		<set name="crystallizable" val="true" />
		<set name="weight" val="1550" />
		<set name="soulshots" val="1" />
		<set name="spiritshots" val="1" />
		<set name="crystal_type" val="a" />
		<set name="p_dam" val="251" />
		<set name="rnd_dam" val="20" />
		<set name="weapon_type" val="blunt" />
		<set name="critical" val="4" />
		<set name="hit_modify" val="4.00000" />
		<set name="atk_speed" val="379" />
		<set name="m_dam" val="121" />
		<set name="crystal_count" val="2824" />
		<set name="item_skill_id" val="3050" /> 
		<set name="item_skill_lvl" val="2" />
		<for>
			<set val="251" order="0x08" stat="pAtk" />
			<set val="121" order="0x08" stat="mAtk" />
			<set val="4" order="0x08" stat="rCrit" />
			<add val="4" order="0x10" stat="accCombat" />
			<set val="379" order="0x08" stat="pAtkSpd" />
			<enchant val="0" order="0x0C" stat="pAtk" />
			<enchant val="0" order="0x0C" stat="mAtk" />
			
			<mul val="1.05" order="0x30" stat="pvpPhysDmg" />
			<mul val="1.05" order="0x30" stat="pvpMagicalDmg" />
			
			<add val="61" order="0x40" stat="rCrit" />
		</for>
	</item>
	<item id="8797" type="Weapon" name="Diapasão do Behemoth - Foco">
		
		<set name="icon" val="icon.weapon_tuning_fork_of_behemoth_i01" />
		<set name="bodypart" val="lrhand" />
		<set name="desc" val="Cristal da Alma: Aumenta o Crítico em 61. Aumenta o dano infligido durante o PvP." />
		<set name="crystallizable" val="true" />
		<set name="weight" val="1890" />
		<set name="soulshots" val="1" />
		<set name="spiritshots" val="1" />
		<set name="crystal_type" val="a" />
		<set name="p_dam" val="305" />
		<set name="rnd_dam" val="20" />
		<set name="weapon_type" val="bigblunt" />
		<set name="critical" val="4" />
		<set name="hit_modify" val="4.00000" />
		<set name="atk_speed" val="325" />
		<set name="m_dam" val="121" />
		<set name="crystal_count" val="2824" />
		<set name="item_skill_id" val="3050" /> 
		<set name="item_skill_lvl" val="2" />
		<for>
			<set val="305" order="0x08" stat="pAtk" />
			<set val="121" order="0x08" stat="mAtk" />
			<set val="4" order="0x08" stat="rCrit" />
			<add val="4" order="0x10" stat="accCombat" />
			<set val="325" order="0x08" stat="pAtkSpd" />
			<enchant val="0" order="0x0C" stat="pAtk" />
			<enchant val="0" order="0x0C" stat="mAtk" />
			
			<mul val="1.05" order="0x30" stat="pvpPhysDmg" />
			<mul val="1.05" order="0x30" stat="pvpMagicalDmg" />
			
			<add val="61" order="0x40" stat="rCrit" />
		</for>
	</item>
	<item id="8798" type="Weapon" name="Diapasão do Behemoth - Vida">
		
		<set name="icon" val="icon.weapon_tuning_fork_of_behemoth_i01" />
		<set name="bodypart" val="lrhand" />
		<set name="desc" val="Cristal da Alma: Aumenta o HP máximo em 25%. Aumenta o dano infligido durante o PvP." />
		<set name="crystallizable" val="true" />
		<set name="weight" val="1890" />
		<set name="soulshots" val="1" />
		<set name="spiritshots" val="1" />
		<set name="crystal_type" val="a" />
		<set name="p_dam" val="305" />
		<set name="rnd_dam" val="20" />
		<set name="weapon_type" val="bigblunt" />
		<set name="critical" val="4" />
		<set name="hit_modify" val="4.00000" />
		<set name="atk_speed" val="325" />
		<set name="m_dam" val="121" />
		<set name="crystal_count" val="2824" />
		<set name="item_skill_id" val="3013" /> 
		<set name="item_skill_lvl" val="4" />
		<for>
			<set val="305" order="0x08" stat="pAtk" />
			<set val="121" order="0x08" stat="mAtk" />
			<set val="4" order="0x08" stat="rCrit" />
			<add val="4" order="0x10" stat="accCombat" />
			<set val="325" order="0x08" stat="pAtkSpd" />
			<enchant val="0" order="0x0C" stat="pAtk" />
			<enchant val="0" order="0x0C" stat="mAtk" />
			
			<mul val="1.05" order="0x30" stat="pvpPhysDmg" />
			<mul val="1.05" order="0x30" stat="pvpMagicalDmg" />
		</for>
	</item>
	<item id="8799" type="Weapon" name="Diapasão do Behemoth - Raiva">
		
		<set name="icon" val="icon.weapon_tuning_fork_of_behemoth_i01" />
		<set name="bodypart" val="lrhand" />
		<set name="desc" val="Cristal da Alma: Diminui o HP máximo em 15% e aumenta o Atq.F em 32. Aumenta o dano ao alvo durante o PvP." />
		<set name="crystallizable" val="true" />
		<set name="weight" val="1890" />
		<set name="soulshots" val="1" />
		<set name="spiritshots" val="1" />
		<set name="crystal_type" val="a" />
		<set name="p_dam" val="305" />
		<set name="rnd_dam" val="20" />
		<set name="weapon_type" val="bigblunt" />
		<set name="critical" val="4" />
		<set name="hit_modify" val="4.00000" />
		<set name="atk_speed" val="325" />
		<set name="m_dam" val="121" />
		<set name="crystal_count" val="2824" />
		<set name="item_skill_id" val="3057" /> 
		<set name="item_skill_lvl" val="1" />
		<for>
			<set val="305" order="0x08" stat="pAtk" />
			<set val="121" order="0x08" stat="mAtk" />
			<set val="4" order="0x08" stat="rCrit" />
			<add val="4" order="0x10" stat="accCombat" />
			<set val="325" order="0x08" stat="pAtkSpd" />
			<enchant val="0" order="0x0C" stat="pAtk" />
			<enchant val="0" order="0x0C" stat="mAtk" />
			
			<mul val="1.05" order="0x30" stat="pvpPhysDmg" />
			<mul val="1.05" order="0x30" stat="pvpMagicalDmg" />
		</for>
	</item>
</list>